psychsim/__init__.py
psychsim/__main__.py
psychsim/action.py
psychsim/agent.py
psychsim/graph.py
psychsim/helper_functions.py
psychsim/modeling.py
psychsim/probability.py
psychsim/reward.py
psychsim/shell.py
psychsim/world.py
psychsim/examples/__init__.py
psychsim/examples/discretize_feature_action.py
psychsim/examples/discretize_feature_in_place.py
psychsim/examples/forward_planning.py
psychsim/examples/forward_planning_tom.py
psychsim/examples/game_theory_tom.py
psychsim/examples/imperfect_action_model.py
psychsim/examples/imperfect_information.py
psychsim/examples/imperfect_observation_model.py
psychsim/examples/non_linear_action_bivariate.py
psychsim/examples/non_linear_action_univariate.py
psychsim/examples/performance_test.py
psychsim/examples/turn_order.py
psychsim/pwl/__init__.py
psychsim/pwl/keys.py
psychsim/pwl/matrix.py
psychsim/pwl/plane.py
psychsim/pwl/state.py
psychsim/pwl/tree.py
psychsim/pwl/vector.py
psychsim/ui/__init__.py
psychsim/ui/diagram.py
psychsim/ui/mainwindow.py
psychsim/ui/mapview.py
psychsim/ui/psychsim_rc.py
psychsim/ui/psychsim_rc2.py
psychsim/ui/psychsim_rc3.py
psychsim/ui/worldview.py
psychsim-1.0.dist-info/LICENSE
psychsim-1.0.dist-info/METADATA
psychsim-1.0.dist-info/WHEEL
psychsim-1.0.dist-info/top_level.txt
psychsim-1.0.dist-info/RECORD
