Metadata-Version: 2.1
Name: psychsim
Version: 1.0
Summary: PsychSim is an open-source social-simulation framework using decision-theoretic agents who have a theory of mind
Home-page: https://github.com/usc-psychsim/psychsim
Author: David Pynadath
Author-email: pynadath@ict.usc.edu
License: UNKNOWN
Platform: UNKNOWN
Classifier: Programming Language :: Python :: 3
Classifier: License :: OSI Approved :: MIT License
Classifier: Operating System :: OS Independent
Requires-Python: >=3.6
